{"cameraMode":{"drawMode":0,"name":"Shaded","section":"Shading Mode"},"sceneLighting":true,"audioPlay":false,"sceneViewState":{"m_AlwaysRefresh":false,"showFog":true,"showSkybox":true,"showFlares":true,"showImageEffects":true,"showParticleSystems":true,"showVisualEffectGraphs":true,"m_FxEnabled":true},"in2DMode":false,"pivot":{"x":-2.2192044258117677,"y":4.0109100341796879,"z":1.4975254535675049},"rotation":{"x":-0.22367925941944123,"y":-0.7713721394538879,"z":0.3686417043209076,"w":-0.46806079149246218},"size":0.5660256147384644,"orthographic":false}